{
  "Donald J. Trump": "president_imgs/45-trump.jpg",
  "Barack Obama": "president_imgs/44-obama.jpg",
  "George W. Bush": "president_imgs/43-bush.jpg",
  "William J. Clinton": "president_imgs/42-clinton.jpg",
  "George Bush": "president_imgs/41-bush.jpg",
  "Ronald Reagan": "president_imgs/40-reagan",
  "Jimmy Carter": "president_imgs/39-carter.jpg",
  "Gerald R. Ford": "president_imgs/38-ford.jpg",
  "Richard Nixon": "president_imgs/37-nixon.jpg",
  "Lyndon B. Johnson": "president_imgs/36-johnson.jpg",
  "John F. Kennedy": "president_imgs/35-kennedy.jpg",
  "Dwight D. Eisenhower": "president_imgs/eisenhower.jpg",
  "Harry S. Truman": "president_imgs/33-truman.jpg",
  "Fraklin D. Roosevelt": "president_img/32-roosevelt.jpg",
  "Herbert Hoover": "president_imgs/31-hoover.jpg",
  "Calvin Coolidge": "president_imgs/30-coolidge.jpg",
  "Warren G. Harding": "president_imgs/29-harding.jpg",
  "Woodrow Wilson": "president_imgs/28-wilson.jpg",
  "William Howard Taft": "president_imgs/27-taft.jpg",
  "Theodore Roosevelt": "president_imgs/26-roosevelt.jpg",
  "William Mckinley": "president_imgs/25-mckinley.jpg",
  "Grover Cleaveland": "president_imgs/22-24-cleaveland.jpg",
  "Benjamin Harrison": "president_imgs/23-harrison.jpg",
  "Chester A. Arthur": "president_imgs/21-arthur.jpg",
  "Rutherford B. Hayes": "president_imgs/19-hayes.jpg",
  "Ulysses S. Grant": "president_imgs/18-grant.jpg",
  "Andrew Johnson": "president_imgs/17-johnson.jpg",
  "Abraham Lincoln": "president_imgs/16-lincoln.jpg",
  "James Buchanan": "president_imgs/15-buchanan.jpg",
  "Franklin Pierce": "president_imgs/14-pierce.jpg",
  "Millard Fillmore": "president_imgs/13-fillmore.jpg",
  "Zachary Taylor": "president_imgs/12-taylor.jpg",
  "James K. Polk": "president_imgs/11-polk.jpg",
  "John Tyler": "president_imgs/10-tyler.jpg",
  "Martin van Buren": "president_imgs/08-van-buren.jpg",
  "Andrew Jackson": "president_imgs/07-jackson.jpg",
  "John Quincy Adams": "president_imgs/06-adams.jpg",
  "James Monroe": "president_imgs/05-monroe.jpg",
  "James Madison": "president_imgs/04-madison.jpg",
  "Thomas Jefferson": "president_imgs/03-jefferson.jpg",
  "John Adams": "president_imgs/02-adams.jpg",
  "George Washington": "president_imgs/01-washington.jpg"
}
